SolverPackage/Solver.py
SolverPackage/__init__.py
SolverDrinkingcode-1.1.0.dist-info/LICENSE
SolverDrinkingcode-1.1.0.dist-info/METADATA
SolverDrinkingcode-1.1.0.dist-info/WHEEL
SolverDrinkingcode-1.1.0.dist-info/top_level.txt
SolverDrinkingcode-1.1.0.dist-info/RECORD
